pycharge/__init__.py
pycharge/main.py
python_charge-0.0.118a0.dist-info/LICENSE
python_charge-0.0.118a0.dist-info/METADATA
python_charge-0.0.118a0.dist-info/WHEEL
python_charge-0.0.118a0.dist-info/top_level.txt
python_charge-0.0.118a0.dist-info/RECORD
