Metadata-Version: 2.1
Name: python-charge
Version: 0.0.118a0
Summary: ML Library
Home-page: https://github.com/ASH1998/pYcharge
Author: Ashutosh Mishra
Author-email: pythonicdevil@gmail.com
License: MIT
Keywords: python,machine learning
Platform: UNKNOWN
Classifier: Development Status :: 1 - Planning
Classifier: Intended Audience :: Developers
Classifier: Programming Language :: Python :: 3
Classifier: Operating System :: Unix
Classifier: Operating System :: MacOS :: MacOS X
Classifier: Operating System :: Microsoft :: Windows
Classifier: Programming Language :: Python :: 3
Classifier: Programming Language :: Python :: 3.7
Classifier: Programming Language :: Python :: 3.8
Classifier: Programming Language :: Python :: 3.9
Requires-Python: >=3.8
